parsehole/ConjunctionParser.py
parsehole/__init__.py
parsehole-2.3.dist-info/LICENSE
parsehole-2.3.dist-info/METADATA
parsehole-2.3.dist-info/WHEEL
parsehole-2.3.dist-info/top_level.txt
parsehole-2.3.dist-info/RECORD
